{
  "generated_at": "2025-12-26T13:29:12.468743+08:00",
  "total_titles_processed": 933,
  "failed_sources": [],
  "trends": [
    {
      "keyword_group": "美股",
      "match_count": 2,
      "titles": [
        {
          "title": "平安夜美股债汇涨，标普新高，黄金失守4500，人民币三连涨，加密货币疲软",
          "url": "https://wallstreetcn.com/articles/3761989",
          "source": "华尔街见闻",
          "ranks": [
            2,
            3
          ],
          "is_new": false,
          "appearance_count": 9,
          "time_info": "[00时33分 ~ 07时25分]"
        },
        {
          "title": "美股今日正常开市，欧洲股市继续休市",
          "url": "https://flash.jin10.com/detail/20251226112952955800",
          "source": "金十数据",
          "ranks": [
            10,
            17
          ],
          "is_new": false,
          "appearance_count": 2,
          "time_info": "[12时02分 ~ 12时41分]"
        }
      ]
    },
    {
      "keyword_group": "谷歌 google gemini",
      "match_count": 1,
      "titles": [
        {
          "title": "英伟达急了？或被谷歌TPU逼到墙角，黄仁勋不惜代价也要“收编”Groq",
          "url": "https://wallstreetcn.com/articles/3762068",
          "source": "华尔街见闻",
          "ranks": [
            9,
            6,
            5
          ],
          "is_new": false,
          "appearance_count": 14,
          "time_info": "[00时33分 ~ 13时29分]"
        }
      ]
    }
  ],
  "report_image_url": "https://github.com/yelike/TrendRadar/img/news.jpg"
}